distribute_setup.py
setup.cfg
setup.py
_cv2_win_fallback/__init__.py
_cv2_win_fallback/cv2.pyd
investigators/__init__.py
investigators/visuals.py
investigators.egg-info/PKG-INFO
investigators.egg-info/SOURCES.txt
investigators.egg-info/dependency_links.txt
investigators.egg-info/requires.txt
investigators.egg-info/top_level.txt
tests/__init__.py
tests/integration/__init__.py
tests/integration/grid (tlbr padding - 1, 2, 3, 4).png
tests/integration/health bar 77%.png
tests/integration/tank 70%.png
tests/integration/test_visuals.py