Metadata-Version: 1.1
Name: investigators
Version: 0.1.4.2
Summary: Achieve various investigations of data by combining easy-to-use investigator classes.
Home-page: http://github.com/kobejohn/investigators
Author: KobeJohn
Author-email: niericentral@gmail.com
License: MIT
Platform: UNKNOWN
Classifier: Development Status :: 4 - Beta
Classifier: Environment :: Console
Classifier: Programming Language :: Python :: 2.7
Classifier: Operating System :: Microsoft :: Windows
